{"stats":{"minecraft:killed":{"minecraft:cow":1},"minecraft:picked_up":{"minecraft:leather":1,"minecraft:beef":1},"minecraft:custom":{"minecraft:time_since_rest":85163,"minecraft:crouch_one_cm":82,"minecraft:sprint_one_cm":34089,"minecraft:play_time":85163,"minecraft:damage_taken":70,"minecraft:walk_one_cm":24696,"minecraft:sneak_time":30,"minecraft:mob_kills":1,"minecraft:jump":442,"minecraft:interact_with_brewingstand":13,"minecraft:damage_dealt":130,"minecraft:leave_game":1,"minecraft:time_since_death":85163,"minecraft:walk_on_water_one_cm":1028,"minecraft:total_world_time":87072,"minecraft:fall_one_cm":3100,"minecraft:fly_one_cm":294933},"minecraft:used":{"minecraft:warden_spawn_egg":2,"minecraft:item_frame":16,"arbalests:deadbeat_crossbow":40,"minecraft:glow_item_frame":5,"minecraft:mace":2,"minecraft:end_crystal":1,"minecraft:wind_charge":13,"minecraft:splash_potion":32,"minecraft:obsidian":1}},"DataVersion":4189}